{"data":{"allWordpressWpMedia":{"edges":[{"node":{"id":"25bd6885-8200-52ac-b026-a086c166b274","caption":"<p>ывавысчмсчмсчсмч</p>\n","source_url":"http://localhost:8888/wp-content/uploads/2020/01/2.png"}},{"node":{"id":"598beebe-9427-5438-8ec7-5e2dbbd56964","caption":"<p>Только качественные растения для вашего сада</p>\n","source_url":"http://localhost:8888/wp-content/uploads/2020/01/3.png"}}]},"wordpressPage":{"acf":{"slider1":["http://localhost:8888/wp-content/uploads/2020/01/3.png","http://localhost:8888/wp-content/uploads/2020/01/2.png","http://localhost:8888/wp-content/uploads/2020/01/1.png"]}},"allWordpressPost":{"edges":[{"node":{"acf":{"descriptPost":"There are lorem ipsum is simply free many variations of ipsum the majority suffered.","fullDescriptPost":"There are lorem ipsum is simply free many variations of ipsum the majority suffered.","imgDescriptPost":{"source_url":"http://localhost:8888/wp-content/uploads/2020/01/Layer_3.png","title":"Layer_3"}},"date":"14.01.2020","wordpress_id":76,"title":"Agriculture Miracle you Don’t Know About","slug":"agriculture-miracle-you-dont-know-about-3","categories":[{"slug":"garden"},{"slug":"news"}]}},{"node":{"acf":{"descriptPost":"There are lorem ipsum is simply free many variations of ipsum the majority suffered.","fullDescriptPost":"There are lorem ipsum is simply free many variations of ipsum the majority suffered.dfsdfsdfsdfsdfsdfsdfsdfsdfsdfsdfs","imgDescriptPost":{"source_url":"http://localhost:8888/wp-content/uploads/2020/01/Layer_4.png","title":"Layer_4"}},"date":"14.01.2020","wordpress_id":72,"title":"Bgriculture Miracle you Don’t Know About","slug":"bgriculture-miracle-you-dont-know-about-2","categories":[{"slug":"news"},{"slug":"about-trees"}]}},{"node":{"acf":{"descriptPost":"There are lorem ipsum is simply free many variations of ipsum the majority suffered.","fullDescriptPost":"There are lorem ipsum is simply free many variations of ipsum the majority suffered. There are lorem ipsum is simply free many variations of ipsum the majority suffered. There are lorem ipsum is simply free many variations of ipsum the majority suffered. There are lorem ipsum is simply free many variations of ipsum the majority suffered. There are lorem ipsum is simply free many variations of ipsum the majority suffered. There are lorem ipsum is simply free many variations of ipsum the majority suffered. There are lorem ipsum is simply free many variations of ipsum the majority suffered. There are lorem ipsum is simply free many variations of ipsum the majority suffered.","imgDescriptPost":{"source_url":"http://localhost:8888/wp-content/uploads/2020/01/Layer_5.png","title":"Layer_5"}},"date":"14.01.2020","wordpress_id":64,"title":"Cgriculture Miracle you Don’t Know About","slug":"cgriculture-miracle-you-dont-know-about","categories":[{"slug":"news"},{"slug":"about-plants"}]}}]}}}